my_model/VERSION
my_model/__init__.py
my_model/config.yml
my_model/pipeline.py
my_model/predict.py
my_model/train_pipeline.py
my_model/config/__init__.py
my_model/config/core.py
my_model/datasets/__init__.py
my_model/datasets/test.csv
my_model/datasets/train.csv
my_model/processing/__init__.py
my_model/processing/data_manager.py
my_model/processing/validation.py
my_model/trained_models/genero_pipe_m0.0.1.pkl
analitica_test-0.0.1.dist-info/METADATA
analitica_test-0.0.1.dist-info/WHEEL
analitica_test-0.0.1.dist-info/top_level.txt
analitica_test-0.0.1.dist-info/RECORD
